{
    "Categoria": "Whisky",
    "Data": "09/05/2022",
    "Descrição": "Whisky Hankey Bannister Original 1000 ml. Whisky Super Premiado!!! Confira as medalhas nas imagens do produto.É  um whisky de qualidade superior, com uma longa e distinta história. Hankey e Bannister deram início à sua parceria em 1757, estabelecendo-se rapidamente como fornecedores das mais conceituadas bebidas espirituosas. Os seus consumidores exclusivos incluíam os Reis George V e Edward VII, bem como Sir Winston Churchill. Durante muitos anos, foi fornecido a uma clientela exclusiva, que apreciou o seu carácter suave e excelência de paladar. Hoje, Hankey Bannister mantém a sua proeminência como uma das melhores marcas de whisky escocês e é exportado para mais de oitenta países em todo o mundo.Origem: Escócia.Volume: 1000 ml.Graduação alcoólica: 40% vol.Um aroma suave, com sabor acentuado, que proporciona profundidade extraCor Caramelo leitoso com tom douradoTem sabor leve, sutil, limpo, doce e picante com toques de mel e final duradouro e agradável *O produto não possui caixa.",
    "Fabricante": "Hankey Bannister",
    "Id do produto": "512",
    "Marcadores": [
        "Volume: 1000 ml.",
        "Um aroma suave, com sabor acentuado, que proporciona profundidade extra",
        "Cor Caramelo leitoso com tom dourado",
        "Tem sabor leve, sutil, limpo, doce e picante com toques de mel e final duradouro e agradável"
    ],
    "Nome": "Whisky Hankey Bannister Original 1000 ml",
    "Origem": "Escócia",
    "Preço com oferta": "799",
    "Preço sem oferta": "799",
    "Teor alcoólico": "40"
}